romancal/__init__.py
romancal/conftest.py
romancal/step.py
romancal/assign_wcs/__init__.py
romancal/assign_wcs/assign_wcs_step.py
romancal/assign_wcs/pointing.py
romancal/assign_wcs/utils.py
romancal/assign_wcs/tests/__init__.py
romancal/assign_wcs/tests/test_wcs.py
romancal/associations/__init__.py
romancal/associations/asn_from_list.py
romancal/associations/association.py
romancal/associations/association_io.py
romancal/associations/config.py
romancal/associations/exceptions.py
romancal/associations/generate.py
romancal/associations/load_as_asn.py
romancal/associations/load_asn.py
romancal/associations/main.py
romancal/associations/mk_skycell_asn_from_skycell_list.py
romancal/associations/mk_skycell_list.py
romancal/associations/pool.py
romancal/associations/registry.py
romancal/associations/skycell_asn.py
romancal/associations/lib/__init__.py
romancal/associations/lib/acid.py
romancal/associations/lib/asn_schema_jw_level3.json
romancal/associations/lib/association_rules.py
romancal/associations/lib/callback_registry.py
romancal/associations/lib/constraint.py
romancal/associations/lib/counter.py
romancal/associations/lib/decorators.py
romancal/associations/lib/diff.py
romancal/associations/lib/dms_base.py
romancal/associations/lib/ioregistry.py
romancal/associations/lib/keyvalue_registry.py
romancal/associations/lib/log_config.py
romancal/associations/lib/member.py
romancal/associations/lib/process_list.py
romancal/associations/lib/product_utils.py
romancal/associations/lib/rules_elpp_base.py
romancal/associations/lib/rules_level2.py
romancal/associations/lib/update_path.py
romancal/associations/lib/utilities.py
romancal/associations/lib/tests/__init__.py
romancal/associations/lib/tests/test_asn_from_list_lib.py
romancal/associations/tests/__init__.py
romancal/associations/tests/helpers.py
romancal/associations/tests/test_asn_from_list.py
romancal/associations/tests/test_constraints.py
romancal/associations/tests/test_generate.py
romancal-0.21.0.dist-info/licenses/LICENSE
romancal-0.21.0.dist-info/METADATA
romancal-0.21.0.dist-info/WHEEL
romancal-0.21.0.dist-info/entry_points.txt
romancal-0.21.0.dist-info/top_level.txt
romancal-0.21.0.dist-info/RECORD
