Metadata-Version: 2.4
Name: romancal
Version: 0.21.0
Summary: Library for calibration of science observations from the Nancy Grace Roman Space Telescope
Author: Roman calibration pipeline developers
Project-URL: tracker, https://github.com/spacetelescope/romancal/issues
Project-URL: documentation, https://roman-pipeline.readthedocs.io/en/stable/
Project-URL: repository, https://github.com/spacetelescope/romancal
Classifier: Intended Audience :: Science/Research
Classifier: Topic :: Scientific/Engineering :: Astronomy
Classifier: Programming Language :: Python :: 3
Requires-Python: <3.14,>=3.11
License-File: LICENSE
Requires-Dist: asdf-astropy>=0.8.0
Requires-Dist: astropy>=6.0.0
Requires-Dist: jsonschema>=4.8
Requires-Dist: numpy>1.26
Requires-Dist: scipy>=1.14.1
Requires-Dist: requests>=2.26
Requires-Dist: photutils>=2.3.0
Requires-Dist: pyarrow>=10.0.1
Requires-Dist: pandas>=2.0.0
Requires-Dist: roman_datamodels<0.29.0,>=0.28.0
Requires-Dist: romanisim<0.12,>=0.11.1
Requires-Dist: asdf<6,>=4.1.0
Requires-Dist: crds>=13.0.2
Requires-Dist: drizzle<2.2,>=2.1.1
Requires-Dist: gwcs<0.27.0,>=0.25.2
Requires-Dist: stcal<1.16.0,>=1.15.1
Requires-Dist: stpipe<0.12.0,>=0.11.0
Requires-Dist: spherical-geometry<1.4,>=1.3.3
Requires-Dist: stsci.imagestats<1.9,>=1.8.3
Provides-Extra: docs
Requires-Dist: matplotlib; extra == "docs"
Requires-Dist: sphinx; extra == "docs"
Requires-Dist: sphinx-astropy; extra == "docs"
Requires-Dist: sphinx-automodapi; extra == "docs"
Requires-Dist: sphinx-rtd-theme; extra == "docs"
Requires-Dist: stsci-rtd-theme; extra == "docs"
Requires-Dist: sphinx-autobuild; extra == "docs"
Provides-Extra: test
Requires-Dist: ci-watson>=0.5.0; extra == "test"
Requires-Dist: pysiaf; extra == "test"
Requires-Dist: pytest>8.0.0; extra == "test"
Requires-Dist: pytest-astropy>=0.11.0; extra == "test"
Requires-Dist: deepdiff; extra == "test"
Requires-Dist: stpreview>=0.6.0; extra == "test"
Provides-Extra: dev
Requires-Dist: pysiaf; extra == "dev"
Requires-Dist: romancal[docs,test]; extra == "dev"
Requires-Dist: tox>4; extra == "dev"
Requires-Dist: pre-commit>3; extra == "dev"
Provides-Extra: sdp
Requires-Dist: pysiaf; extra == "sdp"
Requires-Dist: stpreview>=0.6.0; extra == "sdp"
Requires-Dist: roman-photoz; extra == "sdp"
Dynamic: license-file
